wolf_wo/__init__.py
wolf_wo/wolf_wo.py
wolfsocial-1.0.dist-info/LICENSE
wolfsocial-1.0.dist-info/METADATA
wolfsocial-1.0.dist-info/WHEEL
wolfsocial-1.0.dist-info/top_level.txt
wolfsocial-1.0.dist-info/RECORD
